bilibili_danmaku_tools/__init__.py
bilibili_danmaku_tools/analyze.py
bilibili_danmaku_tools/cli.py
bilibili_danmaku_tools/danmaku_xml.py
bilibili_danmaku_tools/defs.py
bilibili_danmaku_tools/merge.py
bilibili_danmaku_tools/slice.py
bilibili_danmaku_tools-1.0.0.dist-info/LICENSE
bilibili_danmaku_tools-1.0.0.dist-info/METADATA
bilibili_danmaku_tools-1.0.0.dist-info/WHEEL
bilibili_danmaku_tools-1.0.0.dist-info/entry_points.txt
bilibili_danmaku_tools-1.0.0.dist-info/RECORD
