Metadata-Version: 2.1
Name: bilibili-danmaku-tools
Version: 1.0.0
Summary: Merge & split danmaku XML files
License: GPL-3.0-only
Author: Joseph Chris
Author-email: joseph@josephcz.xyz
Requires-Python: >=3.8,<4.0
Classifier: License :: OSI Approved :: GNU General Public License v3 (GPLv3)
Classifier: Programming Language :: Python :: 3
Classifier: Programming Language :: Python :: 3.8
Classifier: Programming Language :: Python :: 3.9
Classifier: Programming Language :: Python :: 3.10
Classifier: Programming Language :: Python :: 3.11
